blurt/__init__.py
blurt/__main__.py
blurt/constants.py
blurt/assets/alert.mp3
blurt/assets/beep.mp3
blurt/assets/blurtpy.png
blurt/core/blurt.py
blurt/core/decorators.py
blurt/core/global_api.py
blurt/core/global_blurt.py
blurt/core/voice_config.py
blurt/drivers/base_driver.py
blurt/drivers/driver_linux.py
blurt/drivers/driver_macos.py
blurt/drivers/driver_windows.py
blurtpy-0.3.1.dist-info/licenses/LICENSE
blurtpy-0.3.1.dist-info/METADATA
blurtpy-0.3.1.dist-info/WHEEL
blurtpy-0.3.1.dist-info/top_level.txt
blurtpy-0.3.1.dist-info/RECORD
