Metadata-Version: 2.4
Name: blurtpy
Version: 0.3.1
Summary: Let your Python scripts speak updates out loud.
Author-email: Buddheshwar Nath Keshari <buddheshwar.nk@gmail.com>
Project-URL: Homepage, https://github.com/buddheshwarnath/blurtpy
Project-URL: PyPI, https://pypi.org/project/blurtpy/
Requires-Python: >=3.7
License-File: LICENSE
Requires-Dist: pyttsx3; sys_platform == "win32"
Dynamic: license-file
